MakePythonGreatAgain/MPGAResponse.py
MakePythonGreatAgain/__init__.py
MakePythonGreatAgain/setup.py
MakePythonGreatAgain/sysinfo/__init__.py
MakePythonGreatAgain/sysinfo/index.py
MakePythonGreatAgain/utils/__init__.py
MakePythonGreatAgain/utils/index.py
sysinfo/__init__.py
sysinfo/setup.py
MakePythonGreatAgain-0.0.1.dist-info/METADATA
MakePythonGreatAgain-0.0.1.dist-info/WHEEL
MakePythonGreatAgain-0.0.1.dist-info/top_level.txt
MakePythonGreatAgain-0.0.1.dist-info/RECORD
