Metadata-Version: 2.1
Name: MakePythonGreatAgain
Version: 0.0.1
Summary: MakePythonGreatAgain is a Python Package for my class
Author: Vinnie
Author-email: contactme@vinniehat.com
Keywords: python,first package
Classifier: Development Status :: 3 - Alpha
Classifier: Intended Audience :: Education
Classifier: Programming Language :: Python :: 2
Classifier: Programming Language :: Python :: 3
Classifier: Operating System :: MacOS :: MacOS X
Classifier: Operating System :: Microsoft :: Windows
